{
  "timestamp": "20251117_212919",
  "config": {
    "dt": 0.1,
    "min_frames": 10,
    "max_frames": 2000,
    "diffusion_params": {
      "normal": {
        "D": 0.3,
        "alpha": 1.0,
        "name": "Normal Diffusion"
      },
      "subdiffusion": {
        "D": 0.15,
        "alpha": 0.45,
        "hurst": 0.3,
        "name": "Subdiffusion (fBm)"
      },
      "confined": {
        "D": 0.12,
        "radius": 0.45,
        "name": "Confined Diffusion"
      },
      "superdiffusion": {
        "D": 0.25,
        "alpha": 1.5,
        "hurst": 0.75,
        "persistence": 0.8,
        "name": "Superdiffusion"
      }
    },
    "rf_params": {
      "n_estimators": 1000,
      "max_depth": 50,
      "min_samples_split": 10,
      "min_samples_leaf": 5,
      "max_features": "sqrt",
      "bootstrap": true,
      "oob_score": true,
      "class_weight": "balanced",
      "random_state": 42,
      "n_jobs": -1
    }
  },
  "feature_names": [
    "alpha",
    "D",
    "hurst_exponent",
    "msd_ratio",
    "msd_plateauness",
    "convex_hull_area",
    "space_exploration_ratio",
    "boundary_proximity_var",
    "rg_saturation",
    "asphericity",
    "efficiency",
    "straightness",
    "mean_cos_theta",
    "persistence_length",
    "vacf_lag1",
    "vacf_min",
    "kurtosis",
    "fractal_dimension",
    "confinement_probability",
    "axial_range",
    "axial_std",
    "axial_ratio",
    "vertical_drift",
    "axial_persistence"
  ],
  "label_mapping": {
    "normal": 0,
    "subdiffusion": 1,
    "confined": 2,
    "superdiffusion": 3
  },
  "training_history": {
    "iterations": [
      1
    ],
    "oob_scores": [
      0.9984375
    ],
    "f1_macro_scores": [
      1.0
    ],
    "n_tracks_per_iteration": [
      {
        "normal": 1000,
        "subdiffusion": 1000,
        "confined": 1000,
        "superdiffusion": 1000
      }
    ]
  },
  "final_performance": {
    "f1_macro": 1.0,
    "oob_score": 0.9984375,
    "report": {
      "0": {
        "precision": 1.0,
        "recall": 1.0,
        "f1-score": 1.0,
        "support": 200.0
      },
      "1": {
        "precision": 1.0,
        "recall": 1.0,
        "f1-score": 1.0,
        "support": 200.0
      },
      "2": {
        "precision": 1.0,
        "recall": 1.0,
        "f1-score": 1.0,
        "support": 200.0
      },
      "3": {
        "precision": 1.0,
        "recall": 1.0,
        "f1-score": 1.0,
        "support": 200.0
      },
      "accuracy": 1.0,
      "macro avg": {
        "precision": 1.0,
        "recall": 1.0,
        "f1-score": 1.0,
        "support": 800.0
      },
      "weighted avg": {
        "precision": 1.0,
        "recall": 1.0,
        "f1-score": 1.0,
        "support": 800.0
      }
    },
    "confusion_matrix": [
      [
        200,
        0,
        0,
        0
      ],
      [
        0,
        200,
        0,
        0
      ],
      [
        0,
        0,
        200,
        0
      ],
      [
        0,
        0,
        0,
        200
      ]
    ]
  },
  "feature_importance": {
    "alpha": 0.04146739191506564,
    "D": 0.031978407699129616,
    "hurst_exponent": 0.04567439629170161,
    "msd_ratio": 0.022177650312111184,
    "msd_plateauness": 0.025878445519211243,
    "convex_hull_area": 0.11221410766686221,
    "space_exploration_ratio": 0.01154075072147912,
    "boundary_proximity_var": 0.02310655157411255,
    "rg_saturation": 5.2162749221872103e-05,
    "asphericity": 0.054193286016259154,
    "efficiency": 0.07642272153972483,
    "straightness": 0.06813906105001362,
    "mean_cos_theta": 0.04906533157858027,
    "persistence_length": 0.03050347532253035,
    "vacf_lag1": 0.08731579814902407,
    "vacf_min": 0.09501171869893468,
    "kurtosis": 0.0008656764316082574,
    "fractal_dimension": 0.0,
    "confinement_probability": 2.2345194465758126e-05,
    "axial_range": 0.060384823173035174,
    "axial_std": 0.05892012499071348,
    "axial_ratio": 0.09809120830567865,
    "vertical_drift": 0.0004216570544626889,
    "axial_persistence": 0.006552908046074058
  }
}